Workbook
Name Slicer_Annual_Report_Category: #N/A
Name Slicer_Annual_Report_Category1: #N/A
Name Slicer_Department: #N/A
Name Slicer_Department1: #N/A
Name Slicer_IPA_Rating_Clean: #N/A
Name Slicer_IPA_Rating_Clean1: #N/A
Name Slicer_Reporting_Year: #N/A

Sheet README
A1: UK Government Major Projects
A2: Cost, Schedule and Delivery-Risk Dashboard
A4: Portfolio analysis of the 2024–25 and 2025–26 NISTA Major Projects datasets
A6: This workbook analyses major UK government projects by department, whole-life cost, schedule duration and delivery-confidence rating. It combines multiple annual datasets through Power Query, models the portfolio in Power Pivot and applies a custom analytical risk score to support project-level prioritisation.
A12: Worksheet | B12: Purpose
A13: Executive Dashboard | B13: Headline portfolio KPIs and year comparison
A14: Departmental Analysis | B14: Department cost and delivery-risk comparison
A15: Project Risk Register | B15: Sortable project-level analytical risk register
A16: Risk Summary | B16: Risk-tier distribution and cost exposure
A17: Data Quality | B17: Record-count validation and data-completeness checks
A18: Methodology | B18: Data preparation, scoring rules and limitations
A19: README | B19: Workbook instructions and project overview
A21: Refresh instructions
A23: 1. Store the annual source CSV files in the designated source-data folder.
A24: 2. Do not manually edit the source CSV files.
A25: 3. Open the workbook and select Data → Refresh All.
A26: 4. Confirm the Data Quality page shows 213 records for 2024–25 and 189 records for 2025–26.
A27: 5. Check that dashboard slicers and PivotTables update successfully
A28: 6.Portfolio viewers can use the cached workbook outputs without the source CSV files; refreshing requires the annual source files in the established source-data folder.
A29: Technical features demonstrated
A31: 1.Power Query for importing, cleaning, standardising and appending annual datasets
A32: 2.Power Pivot relationships between fact and dimension tables
A33: 3.DAX measures for project counts, portfolio cost, duration and rating distribution
A34: 4.Custom 100-point analytical project-risk methodology
... A43: Workbook Details
A45: Item | B45: Value
A46: Author | B46: Wajedul Haque
A47: Tool | B47: Microsoft Excel 365
A48: Reporting years | B48: 2024–25 and 2025–26
A49: Source unit | B49: £ millions in 2024–25 real prices
A50: Data refresh | B50: Power Query
A51: Model | B51: Power Pivot and DAX
A52: Version | B52: 1

Sheet Executive Dashboard
A1: UK Government Major Projects Cost, Schedule and Delivery-Risk Dashboard
A6: Project Records | B6: Average Duration Months | C6: Red or Amber % of Rated Projects | D6: Total Whole Life Cost £bn
A7: 167 | B7: 148.92742 | C7: 0.93413174 | D7: 656.75249
A35: Portfolio reported at 31 March 2026 | Costs presented in 2024–25 real prices
A39: Analytical Risk Score is independently developed and is not an official government project rating.

Sheet Pivot Support
A1: Row Labels | B1: Project Records | F1: Row Labels | G1: Total Whole Life Cost £bn | J1: Project Name | K1: Total Risk Score | M1: Department | N1: GREEN | O1: AMBER | P1: RED
A2: AMBER | B2: 112 | F2: 2024-25 | G2: 336.58353 | J2: {=_xlfn.SORTBY( _xlfn._xlws.FILTER( CHOOSE({1,2}, 'Project Risk Register'!$A$2:$A$190, 'Project Risk Register'!$N$2:$N$190), 'Project Risk Register'!$N$2:$N$190<>""), _xlfn._xlws.FILTER('Project Risk Register'!$N$2:$N$190,'Project Risk Register'!$N$2:$N$190<>""),-1, _xlfn._xlws.FILTER('Project Risk Register'!$F$2:$F$190,'Project Risk Register'!$N$2:$N$190<>""),-1)} -> ARMOURED CAVALRY 2025 | K2: 100 | M2: ='Departmental Analysis'!A26 -> MOD | N2: =COUNTIFS( 'Project Risk Register'!$B$2:$B$190,$M2, 'Project Risk Register'!$I$2:$I$190,N$1) -> 1 | O2: =COUNTIFS( 'Project Risk Register'!$B$2:$B$190,$M2, 'Project Risk Register'!$I$2:$I$190,O$1) -> 10 | P2: =COUNTIFS( 'Project Risk Register'!$B$2:$B$190,$M2, 'Project Risk Register'!$I$2:$I$190,P$1) -> 9
A3: GREEN | B3: 11 | F3: 2025-26 | G3: 320.16896 | J3: ARMOUR MBT 2025 | K3: 95 | M3: ='Departmental Analysis'!A27 -> DFT | N3: =COUNTIFS( 'Project Risk Register'!$B$2:$B$190,$M3, 'Project Risk Register'!$I$2:$I$190,N$1) -> 0 | O3: =COUNTIFS( 'Project Risk Register'!$B$2:$B$190,$M3, 'Project Risk Register'!$I$2:$I$190,O$1) -> 3 | P3: =COUNTIFS( 'Project Risk Register'!$B$2:$B$190,$M3, 'Project Risk Register'!$I$2:$I$190,P$1) -> 3
A4: RED | B4: 44 | F4: Grand Total | G4: 656.75249 | J4: FARMING AND COUNTRYSIDE PROGRAMME | K4: 90 | M4: ='Departmental Analysis'!A28 -> HO | N4: =COUNTIFS( 'Project Risk Register'!$B$2:$B$190,$M4, 'Project Risk Register'!$I$2:$I$190,N$1) -> 0 | O4: =COUNTIFS( 'Project Risk Register'!$B$2:$B$190,$M4, 'Project Risk Register'!$I$2:$I$190,O$1) -> 6 | P4: =COUNTIFS( 'Project Risk Register'!$B$2:$B$190,$M4, 'Project Risk Register'!$I$2:$I$190,P$1) -> 2
J5: Remediation Portfolio | K5: 90 | M5: ='Departmental Analysis'!A29 -> DESNZ | N5: =COUNTIFS( 'Project Risk Register'!$B$2:$B$190,$M5, 'Project Risk Register'!$I$2:$I$190,N$1) -> 0 | O5: =COUNTIFS( 'Project Risk Register'!$B$2:$B$190,$M5, 'Project Risk Register'!$I$2:$I$190,O$1) -> 4 | P5: =COUNTIFS( 'Project Risk Register'!$B$2:$B$190,$M5, 'Project Risk Register'!$I$2:$I$190,P$1) -> 3
J6: EAST COAST DIGITAL PROGRAMME | K6: 90 | M6: ='Departmental Analysis'!A30 -> DHSC | N6: =COUNTIFS( 'Project Risk Register'!$B$2:$B$190,$M6, 'Project Risk Register'!$I$2:$I$190,N$1) -> 1 | O6: =COUNTIFS( 'Project Risk Register'!$B$2:$B$190,$M6, 'Project Risk Register'!$I$2:$I$190,O$1) -> 2 | P6: =COUNTIFS( 'Project Risk Register'!$B$2:$B$190,$M6, 'Project Risk Register'!$I$2:$I$190,P$1) -> 0
J7: SUBMARINE WATERFRONT INFRASTRUCTURE FUTURE | K7: 90 | M7: ='Departmental Analysis'!A31 -> DEFRA | N7: =COUNTIFS( 'Project Risk Register'!$B$2:$B$190,$M7, 'Project Risk Register'!$I$2:$I$190,N$1) -> 2 | O7: =COUNTIFS( 'Project Risk Register'!$B$2:$B$190,$M7, 'Project Risk Register'!$I$2:$I$190,O$1) -> 4 | P7: =COUNTIFS( 'Project Risk Register'!$B$2:$B$190,$M7, 'Project Risk Register'!$I$2:$I$190,P$1) -> 2
J8: NEW HOSPITAL PROGRAMME | K8: 85 | M8: ='Departmental Analysis'!A32 -> MHCLG | N8: =COUNTIFS( 'Project Risk Register'!$B$2:$B$190,$M8, 'Project Risk Register'!$I$2:$I$190,N$1) -> 0 | O8: =COUNTIFS( 'Project Risk Register'!$B$2:$B$190,$M8, 'Project Risk Register'!$I$2:$I$190,O$1) -> 2 | P8: =COUNTIFS( 'Project Risk Register'!$B$2:$B$190,$M8, 'Project Risk Register'!$I$2:$I$190,P$1) -> 1
J9: NORTHERN POWERHOUSE RAIL | K9: 85 | M9: ='Departmental Analysis'!A33 -> DFE | N9: =COUNTIFS( 'Project Risk Register'!$B$2:$B$190,$M9, 'Project Risk Register'!$I$2:$I$190,N$1) -> 1 | O9: =COUNTIFS( 'Project Risk Register'!$B$2:$B$190,$M9, 'Project Risk Register'!$I$2:$I$190,O$1) -> 0 | P9: =COUNTIFS( 'Project Risk Register'!$B$2:$B$190,$M9, 'Project Risk Register'!$I$2:$I$190,P$1) -> 0
J10: Hydrogen Allocation Round 2 (HAR2) | K10: 85 | M10: ='Departmental Analysis'!A34 -> DWP | N10: =COUNTIFS( 'Project Risk Register'!$B$2:$B$190,$M10, 'Project Risk Register'!$I$2:$I$190,N$1) -> 1 | O10: =COUNTIFS( 'Project Risk Register'!$B$2:$B$190,$M10, 'Project Risk Register'!$I$2:$I$190,O$1) -> 5 | P10: =COUNTIFS( 'Project Risk Register'!$B$2:$B$190,$M10, 'Project Risk Register'!$I$2:$I$190,P$1) -> 0
J11: LAND ENVIRONMENT TACTICAL COMMUNICATION AND INFORMATION SYSTEMS | K11: 85 | M11: ='Departmental Analysis'!A35 -> MOJ | N11: =COUNTIFS( 'Project Risk Register'!$B$2:$B$190,$M11, 'Project Risk Register'!$I$2:$I$190,N$1) -> 0 | O11: =COUNTIFS( 'Project Risk Register'!$B$2:$B$190,$M11, 'Project Risk Register'!$I$2:$I$190,O$1) -> 5 | P11: =COUNTIFS( 'Project Risk Register'!$B$2:$B$190,$M11, 'Project Risk Register'!$I$2:$I$190,P$1) -> 2
J12: MECHANISED INFANTRY PROGRAMME | K12: 85
J13: NEW STYLE OF INFORMATION TECHNOLOGY DEPLOYED | K13: 85
J14: GEOLOGICAL DISPOSAL FACILITY | K14: 80
J15: COLLECTIVE TRAINING TRANSFORMATION PROGRAMME | K15: 80
J16: LAND INTELLIGENCE, SURVEILLANCE, TARGET ACQUISITION AND RECONNAISSANCE (ISTAR) | K16: 80
J17: GROUND BASED AIR DEFENCE (GBAD) | K17: 80
J18: Law Enforcement Data Service | K18: 80
J19: CORE PRODUCTION CAPABILITY | K19: 75
J20: COLLECTIONS, PACKAGING AND REFORMS PROGRAMME | K20: 75
J21: FUTURE BORDER AND IMMIGRATION SYSTEM PROGRAMME (FBIS) | K21: 75
J22: SERVICE MODERNISATION PROGRAMME | K22: 75
J23: FUTURE AIR DOMINANCE SYSTEM | K23: 75
... J82: Mobile Fires Platform | K82: 25

Sheet Departmental Analysis
A25: Department | B25: Total Whole Life Cost £m | C25: Red or Amber % | D25: Project Records | E25: Average Duration Months | G25: Department | H25: Total Whole Life Cost £m | J25: Reporting Year | K25: All
A26: MOD | B26: 195988.87 | C26: 0.95 | D26: 91 | E26: 232.56029 | G26: MOJ | H26: 31999.22
A27: DFT | B27: 139441.09 | C27: 1 | D27: 35 | E27: 197.12174 | G27: DWP | H27: 38425.49 | J27: Delivery Rating | K27: Project Records
A28: HO | B28: 135300.67 | C28: 1 | D28: 37 | E28: 89.705 | G28: DFE | H28: 44007.75 | J28: AMBER | K28: 112
A29: DESNZ | B29: 128438.29 | C29: 1 | D29: 40 | E29: 170.56538 | G29: MHCLG | H29: 69374.62 | J29: GREEN | K29: 11
A30: DHSC | B30: 115176.44 | C30: 0.83333333 | D30: 18 | E30: 123.43571 | G30: DEFRA | H30: 83749.57 | J30: RED | K30: 44
A31: DEFRA | B31: 83749.57 | C31: 0.875 | D31: 23 | E31: 107.52 | G31: DHSC | H31: 115176.44 | J31: Grand Total | K31: 167
A32: MHCLG | B32: 69374.62 | C32: 0.9 | D32: 21 | E32: 122.86154 | G32: DESNZ | H32: 128438.29
A33: DFE | B33: 44007.75 | D33: 18 | E33: 86.633333 | G33: HO | H33: 135300.67
A34: DWP | B34: 38425.49 | C34: 0.78571429 | D34: 15 | E34: 111.68 | G34: DFT | H34: 139441.09
A35: MOJ | B35: 31999.22 | C35: 0.93333333 | D35: 36 | E35: 82.286111 | G35: MOD | H35: 195988.87
A36: Grand Total | B36: 981902.01 | C36: 0.92361111 | D36: 334 | E36: 155.44274 | G36: Grand Total | H36: 981902.01

Sheet Project Risk Register
A1: Project Name | B1: Department | C1: Annual Report Category | D1: Major Projects ID | E1: Reporting Year | F1: Whole Life Cost Clean | G1: Duration Months | H1: FY Variance Clean | I1: IPA Rating Clean | J1: Delivery Risk Score | K1: Cost Exposure Score | L1: Duration Exposure Score | M1: Variance Risk Score | N1: Total Risk Score | O1: Risk Tier
A2: ARMOURED CAVALRY 2025 | B2: MOD | C2: Military Capability | D2: MOD_0091_1415-Q3 | E2: 2025-26 | F2: 8935.68 | G2: 183.8 | H2: 23.88 | I2: RED | J2: 40 | K2: 25 | L2: 20 | M2: 15 | N2: 100 | O2: Critical
A3: ARMOUR MBT 2025 | B3: MOD | C3: Military Capability | D3: MOD_0104_1617-Q1 | E3: 2025-26 | F3: 1979.22 | G3: 214.2 | H3: 33.29 | I3: RED | J3: 40 | K3: 20 | L3: 20 | M3: 15 | N3: 95 | O3: Critical
A4: FARMING AND COUNTRYSIDE PROGRAMME | B4: DEFRA | C4: Government Transformation and Service Delivery | D4: DEFRA_0008_2021-Q1 | E4: 2025-26 | F4: 25494.95 | G4: 140 | H4: 9.38 | I4: RED | J4: 40 | K4: 25 | L4: 20 | M4: 5 | N4: 90 | O4: Critical
A5: EAST COAST DIGITAL PROGRAMME | B5: DFT | C5: Infrastructure and Construction | D5: DFT_0038_1920-Q4 | E5: 2025-26 | F5: 3030.39 | G5: 161.4 | H5: 15.88 | I5: RED | J5: 40 | K5: 20 | L5: 20 | M5: 10 | N5: 90 | O5: Critical
A6: Remediation Portfolio | B6: MHCLG | C6: Infrastructure and Construction | D6: DLUHC_0250_2324-Q1 | E6: 2025-26 | F6: 9726.6 | G6: 153.2 | H6: 5.3 | I6: RED | J6: 40 | K6: 25 | L6: 20 | M6: 5 | N6: 90 | O6: Critical
A7: SUBMARINE WATERFRONT INFRASTRUCTURE FUTURE | B7: MOD | C7: Infrastructure and Construction | D7: MOD_0011_2122-Q2 | E7: 2025-26 | F7: 2230.52 | G7: 172.6 | H7: 17.7 | I7: RED | J7: 40 | K7: 20 | L7: 20 | M7: 10 | N7: 90 | O7: Critical
A8: Hydrogen Allocation Round 2 (HAR2) | B8: DESNZ | C8: Infrastructure and Construction | D8: DESNZ_0397_2425-Q2 | E8: 2025-26 | F8: 9427.02 | G8: 216.6 | I8: RED | J8: 40 | K8: 25 | L8: 20 | M8: 0 | N8: 85 | O8: Critical
A9: NORTHERN POWERHOUSE RAIL | B9: DFT | C9: Infrastructure and Construction | D9: DFT_0141_2223-Q1 | E9: 2025-26 | F9: 45000 | G9: 430.9 | H9: 69.79 | I9: AMBER | J9: 25 | K9: 25 | L9: 20 | M9: 15 | N9: 85 | O9: Critical
A10: NEW HOSPITAL PROGRAMME | B10: DHSC | C10: Infrastructure and Construction | D10: DHSC_0066_2021-Q2 | E10: 2025-26 | F10: 47523.91 | G10: 303.1 | H10: 24.01 | I10: AMBER | J10: 25 | K10: 25 | L10: 20 | M10: 15 | N10: 85 | O10: Critical
A11: LAND ENVIRONMENT TACTICAL COMMUNICATION AND INFORMATION SYSTEMS | B11: MOD | C11: Military Capability | D11: MOD_0105_1617-Q1 | E11: 2025-26 | F11: 7734.29 | G11: 266.5 | H11: 47.19 | I11: AMBER | J11: 25 | K11: 25 | L11: 20 | M11: 15 | N11: 85 | O11: Critical
A12: NEW STYLE OF INFORMATION TECHNOLOGY DEPLOYED | B12: MOD | C12: Information and Communications Technology (ICT) | D12: MOD_0109_1617-Q2 | E12: 2025-26 | F12: 1598.79 | G12: 168 | H12: 2.42 | I12: RED | J12: 40 | K12: 20 | L12: 20 | M12: 5 | N12: 85 | O12: Critical
A13: MECHANISED INFANTRY PROGRAMME | B13: MOD | C13: Military Capability | D13: MOD_0115_1718-Q2 | E13: 2025-26 | F13: 5033.66 | G13: 190.4 | H13: 54.27 | I13: AMBER | J13: 25 | K13: 25 | L13: 20 | M13: 15 | N13: 85 | O13: Critical
A14: GEOLOGICAL DISPOSAL FACILITY | B14: DESNZ | C14: Infrastructure and Construction | D14: DECC_0005_1112-Q1 | E14: 2025-26 | F14: 26350.29 | H14: 21.71 | I14: RED | J14: 40 | K14: 25 | L14: 0 | M14: 15 | N14: 80 | O14: Critical
A15: Law Enforcement Data Service | B15: HO | C15: Information and Communications Technology (ICT) | D15: HO_0036_1617-Q2 | E15: 2025-26 | F15: 1086.68 | G15: 153 | H15: 35.18 | I15: AMBER | J15: 25 | K15: 20 | L15: 20 | M15: 15 | N15: 80 | O15: Critical
A16: COLLECTIVE TRAINING TRANSFORMATION PROGRAMME | B16: MOD | C16: Military Capability | D16: MOD_0121_2021-Q4 | E16: 2025-26 | F16: 2083.25 | G16: 261.9 | H16: 23.24 | I16: AMBER | J16: 25 | K16: 20 | L16: 20 | M16: 15 | N16: 80 | O16: Critical
A17: LAND INTELLIGENCE, SURVEILLANCE, TARGET ACQUISITION AND RECONNAISSANCE (ISTAR) | B17: MOD | C17: Military Capability | D17: MOD_0056_2122-Q3 | E17: 2025-26 | F17: 1498.14 | G17: 171.2 | H17: 34.54 | I17: AMBER | J17: 25 | K17: 20 | L17: 20 | M17: 15 | N17: 80 | O17: Critical
A18: GROUND BASED AIR DEFENCE (GBAD) | B18: MOD | C18: Military Capability | D18: MOD_0144_2122-Q1 | E18: 2025-26 | F18: 1454.95 | G18: 186 | H18: 43.75 | I18: AMBER | J18: 25 | K18: 20 | L18: 20 | M18: 15 | N18: 80 | O18: Critical
A19: COLLECTIONS, PACKAGING AND REFORMS PROGRAMME | B19: DEFRA | C19: Government Transformation and Service Delivery | D19: DEFRA_0040_2122-Q3 | E19: 2025-26 | F19: 5204.73 | G19: 122 | H19: 3.24 | I19: AMBER | J19: 25 | K19: 25 | L19: 20 | M19: 5 | N19: 75 | O19: Critical
A20: SERVICE MODERNISATION PROGRAMME | B20: DWP | C20: Government Transformation and Service Delivery | D20: DWP_0217_2223-Q4 | E20: 2025-26 | F20: 1150 | G20: 132 | H20: 13.19 | I20: AMBER | J20: 25 | K20: 20 | L20: 20 | M20: 10 | N20: 75 | O20: Critical
A21: FUTURE BORDER AND IMMIGRATION SYSTEM PROGRAMME (FBIS) | B21: HO | C21: Government Transformation and Service Delivery | D21: HO_0039_1920-Q4 | E21: 2025-26 | F21: 5140.89 | G21: 108 | H21: 18.09 | I21: AMBER | J21: 25 | K21: 25 | L21: 15 | M21: 10 | N21: 75 | O21: Critical
A22: FUTURE AIR DOMINANCE SYSTEM | B22: MOD | C22: Military Capability | D22: MOD_0479_2425-Q4 | E22: 2025-26 | G22: 283 | H22: 30.71 | I22: RED | J22: 40 | K22: 0 | L22: 20 | M22: 15 | N22: 75 | O22: Critical
A23: CORE PRODUCTION CAPABILITY | B23: MOD | C23: Military Capability | D23: MOD_0078_1213-Q1 | E23: 2025-26 | F23: 7784.34 | G23: 380.2 | H23: 7.77 | I23: AMBER | J23: 25 | K23: 25 | L23: 20 | M23: 5 | N23: 75 | O23: Critical
A24: 10K Additional Prison Places Estate Expansion Houseblocks and Refurbishments | B24: MOJ | C24: Infrastructure and Construction | D24: MOJ_0113_2122-Q2 | E24: 2025-26 | G24: 137.7 | H24: 56.9 | I24: RED | J24: 40 | K24: 0 | L24: 20 | M24: 15 | N24: 75 | O24: Critical
A25: 10K Additional Prison Places Estate Expansion Category D | B25: MOJ | C25: Infrastructure and Construction | D25: MOJ_0111_2122-Q2 | E25: 2025-26 | G25: 133.8 | H25: 65.99 | I25: RED | J25: 40 | K25: 0 | L25: 20 | M25: 15 | N25: 75 | O25: Critical
A26: Warm Homes Agency | B26: DESNZ | C26: Government Transformation and Service Delivery | D26: DESNZ_0542_2526-Q2 | E26: 2025-26 | F26: 276.69 | G26: 41.8 | H26: 16.77 | I26: RED | J26: 40 | K26: 10 | L26: 10 | M26: 10 | N26: 70 | O26: Critical
A27: LOWER THAMES CROSSING | B27: DFT | C27: Infrastructure and Construction | D27: DFT_0022_1415-Q4 | E27: 2025-26 | F27: 9899.54 | G27: 254 | H27: 0 | I27: AMBER | J27: 25 | K27: 25 | L27: 20 | M27: 0 | N27: 70 | O27: Critical
A28: Health Transformation Programme | B28: DWP | C28: Government Transformation and Service Delivery | D28: DWP_0028_1819-Q3 | E28: 2025-26 | F28: 735.46 | G28: 138 | H28: 10.98 | I28: AMBER | J28: 25 | K28: 15 | L28: 20 | M28: 10 | N28: 70 | O28: Critical
A29: Workplace Transformation | B29: DWP | C29: Government Transformation and Service Delivery | D29: DWP_0013_2122-Q2 | E29: 2025-26 | F29: 3367.17 | G29: 128.9 | H29: 2.09 | I29: AMBER | J29: 25 | K29: 20 | L29: 20 | M29: 5 | N29: 70 | O29: Critical
A30: UNITY PROGRAMME | B30: HMRC | C30: Government Transformation and Service Delivery | D30: HMRC_0031_2122-Q3 | E30: 2025-26 | F30: 245.97 | G30: 86.9 | H30: 0.29 | I30: RED | J30: 40 | K30: 10 | L30: 15 | M30: 5 | N30: 70 | O30: Critical
A31: MAKING TAX DIGITAL | B31: HMRC | C31: Information and Communications Technology (ICT) | D31: HMRC_0017_1617-Q2 | E31: 2025-26 | F31: 1484.62 | G31: 155.9 | H31: 0.34 | I31: AMBER | J31: 25 | K31: 20 | L31: 20 | M31: 5 | N31: 70 | O31: Critical
A32: HOME OFFICE BIOMETRICS (HOB) PROGRAMME | B32: HO | C32: Information and Communications Technology (ICT) | D32: HO_0033_1415-Q3 | E32: 2025-26 | F32: 1809.85 | G32: 153 | H32: 2.74 | I32: AMBER | J32: 25 | K32: 20 | L32: 20 | M32: 5 | N32: 70 | O32: Critical
A33: CLYDE INFRASTRUCTURE | B33: MOD | C33: Military Capability | D33: MOD_0118_1718-Q3 | E33: 2025-26 | F33: 3324.98 | G33: 198.8 | H33: 7.43 | I33: AMBER | J33: 25 | K33: 20 | L33: 20 | M33: 5 | N33: 70 | O33: Critical
A34: SOCIAL HOUSING DECARBONISATION FUND | B34: DESNZ | C34: Infrastructure and Construction | D34: BEIS_0014_2021-Q4 | E34: 2025-26 | F34: 2256.29 | G34: 114.7 | H34: 0.12 | I34: AMBER | J34: 25 | K34: 20 | L34: 15 | M34: 5 | N34: 65 | O34: High
A35: FRONTLINE DIGITISATION | B35: DHSC | C35: Information and Communications Technology (ICT) | D35: DHSC_0071_2122-Q1 | E35: 2025-26 | F35: 2080.52 | G35: 60 | H35: 2.61 | I35: AMBER | J35: 25 | K35: 20 | L35: 15 | M35: 5 | N35: 65 | O35: High
A36: SYNERGY PROGRAMME | B36: DWP | C36: Government Transformation and Service Delivery | D36: DWP_0042_2122-Q3 | E36: 2025-26 | F36: 1990.99 | G36: 94 | H36: 5.21 | I36: AMBER | J36: 25 | K36: 20 | L36: 15 | M36: 5 | N36: 65 | O36: High
A37: EMERGENCY SERVICES MOBILE COMMUNICATIONS | B37: HO | C37: Information and Communications Technology (ICT) | D37: HO_0016_1213-Q1 | E37: 2025-26 | F37: 18139.58 | H37: 49.93 | I37: AMBER | J37: 25 | K37: 25 | L37: 0 | M37: 15 | N37: 65 | O37: High
A38: Affordable Homes Programme (AHP) | B38: MHCLG | C38: Infrastructure and Construction | D38: DLUHC_0138_2223-Q1 | E38: 2025-26 | F38: 12230.5 | G38: 110.8 | H38: 0 | I38: AMBER | J38: 25 | K38: 25 | L38: 15 | M38: 0 | N38: 65 | O38: High
A39: Electronic Monitoring Expansion | B39: MOJ | C39: Government Transformation and Service Delivery | D39: MOJ_0058_2122-Q1 | E39: 2025-26 | F39: 1161.1 | G39: 65.4 | H39: 6.34 | I39: AMBER | J39: 25 | K39: 20 | L39: 15 | M39: 5 | N39: 65 | O39: High
A40: Manchester Digital Campus | B40: CO | C40: Infrastructure and Construction | D40: CO_0438_2425-Q3 | E40: 2025-26 | F40: 1029.78 | G40: 92.3 | H40: 0 | I40: AMBER | J40: 25 | K40: 20 | L40: 15 | M40: 0 | N40: 60 | O40: High
A41: 4th National Lottery Licence | B41: DCMS | C41: Government Transformation and Service Delivery | D41: DCMS_0013_1819-Q3 | E41: 2025-26 | F41: 174.46 | G41: 90.4 | H41: 15.42 | I41: AMBER | J41: 25 | K41: 10 | L41: 15 | M41: 10 | N41: 60 | O41: High
A42: Livestock Information Transformation Programme | B42: DEFRA | C42: Government Transformation and Service Delivery | D42: DEFRA_0348_2324-Q4 | E42: 2025-26 | F42: 525.5 | H42: 2.18 | I42: RED | J42: 40 | K42: 15 | L42: 0 | M42: 5 | N42: 60 | O42: High
A43: National Biosecurity Centre (Weybridge) | B43: DEFRA | C43: Infrastructure and Construction | D43: DEFRA_0007_2021-Q1 | E43: 2025-26 | F43: 2485.6 | G43: 186 | H43: 33.64 | I43: GREEN | J43: 5 | K43: 20 | L43: 20 | M43: 15 | N43: 60 | O43: High
A44: Warm Homes: Local Grant | B44: DESNZ | C44: Infrastructure and Construction | D44: DESNZ_0471_2425-Q4 | E44: 2025-26 | F44: 454.52 | G44: 47.9 | H44: 37.35 | I44: AMBER | J44: 25 | K44: 10 | L44: 10 | M44: 15 | N44: 60 | O44: High
A45: GOV.UK One Login | B45: DSIT | C45: Government Transformation and Service Delivery | D45: CO_0033_2122-Q1 | E45: 2025-26 | F45: 708.86 | G45: 86.8 | H45: 5.7 | I45: AMBER | J45: 25 | K45: 15 | L45: 15 | M45: 5 | N45: 60 | O45: High
A46: Enterprise Customer Relationship Management (eCRM) | B46: HMRC | C46: Government Transformation and Service Delivery | D46: HMRC_0543_2526-Q2 | E46: 2025-26 | F46: 256.75 | G46: 59.9 | H46: 35.83 | I46: AMBER | J46: 25 | K46: 10 | L46: 10 | M46: 15 | N46: 60 | O46: High
A47: SKYNET 6 (AKA FBLOS) | B47: MOD | C47: Information and Communications Technology (ICT) | D47: MOD_0100_1516-Q1 | E47: 2025-26 | G47: 371.9 | I47: RED | J47: 40 | K47: 0 | L47: 20 | M47: 0 | N47: 60 | O47: High
A48: TYPE 31 | B48: MOD | C48: Military Capability | D48: MOD_0112_1718-Q1 | E48: 2025-26 | G48: 208 | I48: RED | J48: 40 | K48: 0 | L48: 20 | M48: 0 | N48: 60 | O48: High
A49: POST OFFICE - TRANSFORMATION | B49: DBT | C49: Information and Communications Technology (ICT) | D49: DBT_0293_2324-Q3 | E49: 2025-26 | F49: 1553.73 | H49: 15.31 | I49: AMBER | J49: 25 | K49: 20 | L49: 0 | M49: 10 | N49: 55 | O49: High
A50: EU Delivery Programme | B50: DEFRA | C50: Government Transformation and Service Delivery | D50: DEFRA_0587_2526-Q3 | E50: 2025-26 | F50: 832.04 | H50: 29.19 | I50: AMBER | J50: 25 | K50: 15 | L50: 0 | M50: 15 | N50: 55 | O50: High
A51: Flood and Coastal Risk Management (FCRM) Investment Programme 2026-2029 | B51: DEFRA | C51: Infrastructure and Construction | E51: 2025-26 | F51: 3861.52 | G51: 36 | I51: AMBER | J51: 25 | K51: 20 | L51: 10 | M51: 0 | N51: 55 | O51: High
A52: Contact Centre as a Service (CCaaS) | B52: HMRC | C52: Government Transformation and Service Delivery | D52: HMRC_0544_2526-Q2 | E52: 2025-26 | F52: 571.86 | G52: 30.9 | H52: 10.87 | I52: AMBER | J52: 25 | K52: 15 | L52: 5 | M52: 10 | N52: 55 | O52: High
A53: NEXT GENERATION (FIXED) COMMUNICATION NETWORK | B53: MOD | C53: Information and Communications Technology (ICT) | D53: MOD_0126_2021-Q4 | E53: 2025-26 | G53: 106.9 | I53: RED | J53: 40 | K53: 0 | L53: 15 | M53: 0 | N53: 55 | O53: High
A54: Small Secure Houseblocks | B54: MOJ | C54: Infrastructure and Construction | D54: MOJ_0144_2223-Q2 | E54: 2025-26 | G54: 83.4 | H54: 30.23 | I54: AMBER | J54: 25 | K54: 0 | L54: 15 | M54: 15 | N54: 55 | O54: High
A55: Rapid Deployment Cells Project | B55: MOJ | C55: Infrastructure and Construction | D55: MOJ_0057_2122-Q1 | E55: 2025-26 | G55: 84.1 | H55: 28.85 | I55: AMBER | J55: 25 | K55: 0 | L55: 15 | M55: 15 | N55: 55 | O55: High
A56: Accelerated Houseblocks | B56: MOJ | C56: Infrastructure and Construction | D56: MOJ_0053_2021-Q4 | E56: 2025-26 | G56: 121.1 | H56: 16.07 | I56: AMBER | J56: 25 | K56: 0 | L56: 20 | M56: 10 | N56: 55 | O56: High
A57: VOA NextGen Rating Programme | B57: VOA | C57: Government Transformation and Service Delivery | D57: HMRC_0143_2223-Q2 | E57: 2025-26 | F57: 300.38 | G57: 66 | H57: 5.53 | I57: AMBER | J57: 25 | K57: 10 | L57: 15 | M57: 5 | N57: 55 | O57: High
A58: Spherical Tokamak for Energy Production | B58: DESNZ | C58: Infrastructure and Construction | D58: BEIS_0153_2223-Q2 | E58: 2025-26 | G58: 320.5 | H58: 0.63 | I58: AMBER | J58: 25 | K58: 0 | L58: 20 | M58: 5 | N58: 50 | O58: High
A59: PENSIONS DASHBOARD PROGRAMME | B59: DWP | C59: Information and Communications Technology (ICT) | D59: DWP_0029_2021-Q4 | E59: 2025-26 | G59: 96 | H59: 11.19 | I59: AMBER | J59: 25 | K59: 0 | L59: 15 | M59: 10 | N59: 50 | O59: High
A60: Police National Database (PND) | B60: HO | C60: Information and Communications Technology (ICT) | D60: HO_0331_2324-Q4 | E60: 2025-26 | F60: 282.64 | H60: 74.22 | I60: AMBER | J60: 25 | K60: 10 | L60: 0 | M60: 15 | N60: 50 | O60: High
A61: MODNET EVOLVE | B61: MOD | C61: Information and Communications Technology (ICT) | D61: MOD_0110_1718-Q1 | E61: 2025-26 | F61: 309.19 | G61: 125 | H61: 38.37 | I61: GREEN | J61: 5 | K61: 10 | L61: 20 | M61: 15 | N61: 50 | O61: High
A62: MENSA | B62: MOD | C62: Military Capability | D62: MOD_0132_2122-Q1 | E62: 2025-26 | F62: 3555.91 | H62: 2.6 | I62: AMBER | J62: 25 | K62: 20 | L62: 0 | M62: 5 | N62: 50 | O62: High
A63: 10k Additional Prison Places - New Build | B63: MOJ | C63: Infrastructure and Construction | D63: MOJ_0050_2021-Q1 | E63: 2025-26 | G63: 146.9 | H63: 2.38 | I63: AMBER | J63: 25 | K63: 0 | L63: 20 | M63: 5 | N63: 50 | O63: High
A64: EURO 2028 | B64: DCMS | C64: Government Transformation and Service Delivery | D64: DCMS_0321_2324-Q3 | E64: 2025-26 | F64: 511.63 | H64: 2.05 | I64: AMBER | J64: 25 | K64: 15 | L64: 0 | M64: 5 | N64: 45 | O64: Medium
A65: FLOOD AND COASTAL EROSION RISK MANAGEMENT | B65: DEFRA | C65: Infrastructure and Construction | D65: DEFRA_0236_2324-Q1 | E65: 2025-26 | F65: 4835.25 | G65: 71.9 | H65: 1.8 | I65: GREEN | J65: 5 | K65: 20 | L65: 15 | M65: 5 | N65: 45 | O65: Medium
A66: NATURE FOR CLIMATE FUND | B66: DEFRA | C66: Infrastructure and Construction | D66: DEFRA_0013_2021-Q4 | E66: 2025-26 | F66: 1272.06 | H66: 0 | I66: AMBER | J66: 25 | K66: 20 | L66: 0 | M66: 0 | N66: 45 | O66: Medium
A67: PUBLIC OWNERSHIP TRANSITION PROGRAMME | B67: DFT | C67: Government Transformation and Service Delivery | D67: DFT_0439_2425-Q3 | E67: 2025-26 | F67: 36.6 | G67: 36.9 | H67: 9.81 | I67: AMBER | J67: 25 | K67: 5 | L67: 10 | M67: 5 | N67: 45 | O67: Medium
A68: ASYLUM TRANSFORMATION PROGRAMME | B68: HO | C68: Government Transformation and Service Delivery | D68: HO_0183_2223-Q3 | E68: 2025-26 | F68: 429.95 | H68: 16.1 | I68: AMBER | J68: 25 | K68: 10 | L68: 0 | M68: 10 | N68: 45 | O68: Medium
A69: SUBMERSIBLE SHIP NUCLEAR AUKUS | B69: MOD | C69: Military Capability | D69: MOD_0007_2122-Q2 | E69: 2025-26 | G69: 348.9 | I69: AMBER | J69: 25 | K69: 0 | L69: 20 | M69: 0 | N69: 45 | O69: Medium
A70: FUTURE COMBAT AIR SYSTEM | B70: MOD | C70: Military Capability | D70: MOD_0122_2021-Q4 | E70: 2025-26 | H70: 4.65 | I70: RED | J70: 40 | K70: 0 | L70: 0 | M70: 5 | N70: 45 | O70: Medium
A71: HS2 PHASE I | B71: DFT | C71: Infrastructure and Construction | D71: DFT_0040_2021-Q1 | E71: 2025-26 | H71: 0 | I71: RED | J71: 40 | K71: 0 | L71: 0 | M71: 0 | N71: 40 | O71: Medium
A72: Rail Reform: Stand-Up of GBR | B72: DFT | C72: Government Transformation and Service Delivery | D72: DFT_0413_2425-Q2 | E72: 2025-26 | I72: RED | J72: 40 | K72: 0 | L72: 0 | M72: 0 | N72: 40 | O72: Medium
A73: NS&I Transformation | B73: HMT | C73: Government Transformation and Service Delivery | D73: HMT_0004_2021-Q2 | E73: 2025-26 | I73: RED | J73: 40 | K73: 0 | L73: 0 | M73: 0 | N73: 40 | O73: Medium
A74: Asylum Support Accommodation Programme | B74: HO | C74: Government Transformation and Service Delivery | D74: HO_0286_2324-Q2 | E74: 2025-26 | I74: RED | J74: 40 | K74: 0 | L74: 0 | M74: 0 | N74: 40 | O74: Medium
A75: ASYLUM ACCOMMODATION PROGRAMME (AAP) | B75: HO | C75: Government Transformation and Service Delivery | D75: HO_0149_2223-Q2 | E75: 2025-26 | I75: RED | J75: 40 | K75: 0 | L75: 0 | M75: 0 | N75: 40 | O75: Medium
A76: INTEGRATED SINGLE FINANCIAL ENVIRONMENT | B76: DHSC | C76: Information and Communications Technology (ICT) | D76: DHSC_0067_2021-Q3 | E76: 2025-26 | F76: 187.99 | G76: 92 | H76: 0.97 | I76: GREEN | J76: 5 | K76: 10 | L76: 15 | M76: 5 | N76: 35 | O76: Medium
A77: DIGITAL PLANNING PROGRAMME | B77: MHCLG | C77: Government Transformation and Service Delivery | D77: DLUHC_0181_2223-Q3 | E77: 2025-26 | F77: 218.54 | H77: 0 | I77: AMBER | J77: 25 | K77: 10 | L77: 0 | M77: 0 | N77: 35 | O77: Medium
A78: Early Years Childcare Reform Programme | B78: DFE | C78: Government Transformation and Service Delivery | D78: DFE_0272_2324-Q2 | E78: 2025-26 | F78: 16207.65 | H78: 0 | I78: GREEN | J78: 5 | K78: 25 | L78: 0 | M78: 0 | N78: 30 | O78: Medium
A79: Connect to Work | B79: DWP | C79: Government Transformation and Service Delivery | D79: DWP_0304_2324-Q3 | E79: 2025-26 | F79: 1094.99 | H79: 1.47 | I79: GREEN | J79: 5 | K79: 20 | L79: 0 | M79: 5 | N79: 30 | O79: Medium
A80: Strategic Sites Accelerator (SSA) | B80: DBT | C80: Infrastructure and Construction | D80: DBT_0296_2526-Q2 | E80: 2025-26 | I80: AMBER | J80: 25 | K80: 0 | L80: 0 | M80: 0 | N80: 25 | O80: Low
A81: Great British Energy | B81: DESNZ | C81: Infrastructure and Construction | D81: DESNZ_0472_2425-Q4 | E81: 2025-26 | I81: AMBER | J81: 25 | K81: 0 | L81: 0 | M81: 0 | N81: 25 | O81: Low
A82: Mobile Fires Platform | B82: MOD | C82: Military Capability | D82: MOD_0527_2526-Q1 | E82: 2025-26 | I82: AMBER | J82: 25 | K82: 0 | L82: 0 | M82: 0 | N82: 25 | O82: Low
A83: Falcon Programme | B83: CO | C83: Government Transformation and Service Delivery | D83: CO_0176_2223-Q3 | E83: 2025-26 | F83: 23.11 | G83: 56 | H83: 41.38 | K83: 5 | L83: 10 | M83: 15 | O83: Not scored
A84: Future Service Programme | B84: CO | C84: Information and Communications Technology (ICT) | D84: CO_0027_2021-Q4 | E84: 2025-26 | G84: 75 | K84: 0 | L84: 15 | M84: 0 | O84: Not scored
A85: Transforming Public Procurement | B85: CO | C85: Government Transformation and Service Delivery | D85: CO_0120_2223-Q1 | E85: 2025-26 | F85: 32.47 | G85: 62.9 | H85: 31.96 | K85: 5 | L85: 15 | M85: 15 | O85: Not scored
A86: Drive 35 | B86: DBT | C86: Infrastructure and Construction | D86: DBT_0295_2526-Q2 | E86: 2025-26 | F86: 1841.78 | H86: 5.18 | K86: 20 | L86: 0 | M86: 5 | O86: Not scored
A87: AUTOMOTIVE TRANSFORMATION FUND (ATF) | B87: DBT | C87: Infrastructure and Construction | D87: BEIS_0090_2122-Q4 | E87: 2025-26 | F87: 702.72 | H87: 82.68 | K87: 15 | L87: 0 | M87: 15 | O87: Not scored
A88: British Museum - Energy Centre Programme (ECP) | B88: DCMS | C88: Infrastructure and Construction | D88: DCMS_0254_2324-Q1 | E88: 2025-26 | F88: 181.97 | G88: 93 | H88: 0 | K88: 10 | L88: 15 | M88: 0 | O88: Not scored
A89: Youth Investment Fund | B89: DCMS | C89: Infrastructure and Construction | D89: DCMS_0118_2223-Q1 | E89: 2025-26 | F89: 360.15 | H89: 5.71 | K89: 10 | L89: 0 | M89: 5 | O89: Not scored
A90: Natural History Museum Unlocked | B90: DCMS | C90: Infrastructure and Construction | D90: DCMS_0018_2021-Q3 | E90: 2025-26 | F90: 213.15 | H90: 0.14 | K90: 10 | L90: 0 | M90: 5 | O90: Not scored
A91: NORTHERN IRELAND | B91: DEFRA | C91: Government Transformation and Service Delivery | D91: DEFRA_0015_2122-Q1 | E91: 2025-26 | F91: 430.55 | G91: 61.3 | H91: 9.92 | K91: 10 | L91: 15 | M91: 5 | O91: Not scored
A92: NO2 PROGRAMME | B92: DEFRA | C92: Infrastructure and Construction | D92: DEFRA_0014_2021-Q4 | E92: 2025-26 | F92: 843.04 | G92: 122.9 | H92: 16.52 | K92: 15 | L92: 20 | M92: 10 | O92: Not scored
A93: TERRESTRIAL NATURAL CAPITAL ECOSYSTEM ASSESSMENT | B93: DEFRA | C93: Government Transformation and Service Delivery | D93: DEFRA_0190_2223-Q3 | E93: 2025-26 | F93: 325.68 | G93: 96 | H93: 1.5 | K93: 10 | L93: 15 | M93: 5 | O93: Not scored
A94: Cefas Infrastructure to Support Future Delivery at Sea | B94: DEFRA | C94: Government Transformation and Service Delivery | D94: DEFRA_0349_2324-Q4 | E94: 2025-26 | F94: 152.89 | K94: 10 | L94: 0 | M94: 0 | O94: Not scored
A95: Boiler Upgrade Scheme | B95: DESNZ | C95: Infrastructure and Construction | D95: DESNZ_0375_2425-Q1 | E95: 2025-26 | F95: 3054.03 | H95: 17.86 | K95: 20 | L95: 0 | M95: 10 | O95: Not scored
A96: SELLAFIELD PRODUCT AND RESIDUE STORE RETREATMENT PLANT PROJECT | B96: DESNZ | C96: Infrastructure and Construction | D96: BEIS_0008_2021-Q3 | E96: 2025-26 | F96: 1432.89 | G96: 231.7 | H96: 11.32 | K96: 20 | L96: 20 | M96: 10 | O96: Not scored
A97: Review of Electricity Market Arrangements (REMA) | B97: DESNZ | C97: Government Transformation and Service Delivery | D97: DESNZ_0333_2324-Q4 | E97: 2025-26 | F97: 29.18 | G97: 26.8 | H97: 53.38 | K97: 5 | L97: 5 | M97: 15 | O97: Not scored
A98: GREEN HEAT NETWORK FUND | B98: DESNZ | C98: Infrastructure and Construction | D98: BEIS_0115_2223-Q1 | E98: 2025-26 | F98: 730.01 | G98: 96.7 | H98: 1.54 | K98: 15 | L98: 15 | M98: 5 | O98: Not scored
A99: HyNet Cluster | B99: DESNZ | C99: Infrastructure and Construction | D99: DESNZ_0457_2425-Q3 | E99: 2025-26 | K99: 0 | L99: 0 | M99: 0 | O99: Not scored
A100: GBE-N SMR Programme | B100: DESNZ | C100: Infrastructure and Construction | D100: BEIS_0233_2223-Q4 | E100: 2025-26 | K100: 0 | L100: 0 | M100: 0 | O100: Not scored
...

Sheet Risk Summary
A1: Risk scoring combines delivery confidence, whole-life cost exposure, project duration and financial-year variance.
C32: Risk Tier | D32: Project Count | E32: Total Whole-Life Cost £m | F32: Average Risk Score | H32: Risk Tier | I32: Count of Project Name
C33: Critical | D33: 32 | E33: 240612.58 | F33: 79.6875 | H33: Critical | I33: 32
C34: High | D34: 30 | E34: 54761.72 | F34: 57.5 | H34: High | I34: 30
C35: Medium | D35: 16 | E35: 24794.66 | F35: 40.3125 | H35: Medium | I35: 16
C36: Low | D36: 3 | F36: 25 | H36: Low | I36: 3
C37: Not scored | D37: 108 | E37: 143883.7 | H37: Grand Total | I37: 81
C38: Grand Total | D38: 189 | E38: 464052.66 | F38: 61.666667

Sheet Data Quality
A1: Portfolio Validation
A3: Confirms record counts, rating distribution and whole-life cost totals after refresh.
A5: Reporting Year | B5: Count of Project Name | C5: Sum of Whole Life Cost Clean | E5: Reporting Year | F5: Project Records | G5: Missing Cost Projects | H5: Missing Duration Projects | I5: Unrated Projects | J5: Cost Data Coverage % | K5: Duration Data Coverage %
A6: 2024-25 | B6: 213 | C6: 565707.28 | E6: 2024-25 | F6: 213 | G6: 56 | H6: 59 | I6: 127 | J6: 0.7370892 | K6: 0.72300469
A7: AMBER | B7: 61 | C7: 213382.35 | E7: 2025-26 | F7: 189 | G7: 56 | H7: 57 | I7: 108 | J7: 0.7037037 | K7: 0.6984127
A8: GREEN | B8: 5 | C8: 20339.06 | E8: Grand Total | F8: 402 | G8: 112 | H8: 116 | I8: 235 | J8: 0.72139303 | K8: 0.71144279
A9: RED | B9: 20 | C9: 102862.12
A10: (blank) | B10: 127 | C10: 229123.75
A11: 2025-26 | B11: 189 | C11: 464052.66
A12: AMBER | B12: 51 | C12: 205226.67
A13: GREEN | B13: 6 | C13: 25120.67
A14: RED | B14: 24 | C14: 89821.62
A15: (blank) | B15: 108 | C15: 143883.7
A16: Grand Total | B16: 402 | C16: 1029759.9

Sheet Methodology
A1: Methodology and Assumptions
A5: UK Government Major Projects | Cost, Schedule and Delivery-Risk Dashboard
A8: 1. Purpose
A10: This workbook analyses UK Government Major Projects across the 2024–25 and 2025–26 reporting periods. It compares project cost, duration, departmental responsibility and delivery-confidence ratings, and applies a custom analytical risk score to support portfolio-level prioritisation.
A14: 2. Data Sources
A16: Item | B16: Description
A17: Source | B17: NISTA Major Projects Annual Report dataset
A18: Reporting Periods | B18: 2024–25 and 2025–26
A19: Grain | B19: One row per project per reporting period
A20: Cost unit | B20: £ millions, presented in 2024–25 real prices
A21: Refresh method | B21: Power Query
A22: Analytical model | B22: Excel Data Model and Power Pivot
A24: Original text fields are retained where the source contains exemptions, planning-stage notes or ranges. Separate cleaned numeric and date fields are used for analysis.
A27: 3. Data Preparation Rules
A29: Field | B29: Cleaning rule
A30: Department | B30: Trimmed, cleaned and standardised to uppercase for relationships
A31: Reporting Year | B31: Added during Power Query import
A32: Start Date | B32: Valid UK-format dates converted; other text becomes null
A33: End Date | B33: Valid UK-format dates converted; ranges may remain unavailable
A34: Duration Months | B34: Days between clean start and end dates divided by 30.44
A35: Whole-Life Cost | B35: Numeric values retained; midpoint used for Low/Mid/High ranges
A36: Benefits | B36: Numeric values retained; midpoint used where a range is supplied
A37: IPA Rating | B37: Standardised to RED, AMBER or GREEN
A38: Missing/exempt values | B38: Retained in original fields and represented as null analytically
A40: 4. Analytical Risk Score
A42: The risk score is an independently developed analytical indicator. It is not an official NISTA or departmental project rating.
A44: Component | B44: Rule | C44: Points
A45: Delivery confidence | B45: Green | C45: 5
B46: Amber | C46: 25
B47: Red | C47: 40
A48: Cost exposure | B48: Under £100m | C48: 5
B49: £100m–£500m | C49: 10
B50: £500m–£1bn | C50: 15
B51: £1bn–£5bn | C51: 20
B52: £5bn+ | C52: 25
A53: Duration exposure | B53: Under 3 years | C53: 5
B54: 3–5 years | C54: 10
B55: 5–10 years | C55: 15
B56: 10+ years | C56: 20
A57: Financial variance | B57: 0% or lower | C57: 0
B58: Above 0% | C58: 5
B59: 10% or above | C59: 10
B60: 20% or above | C60: 15
A62: Maximum possible score: 100
A64: 5. Risk Tier Thresholds
A66: Risk Tier | B66: Total Risk Score | C66: Interpretation
A67: Critical | B67: 70–100 | C67: Highest analytical exposure
A68: High | B68: 50–69 | C68: Elevated analytical exposure
A69: Medium | B69: 30–49 | C69: Moderate analytical exposure
A70: Low | B70: Below 30 | C70: Lower analytical exposure
A71: Not scored | B71: No usable IPA rating | C71: No total analytical risk score assigned
A73: 6. Assumptions and Limitations
A75: 1.A high-value or long-duration project is not necessarily poorly managed; these factors represent exposure, not failure.
A76: 2.The financial variance field represents the reported financial-year position, not necessarily whole-life cost overruns.
A77: 3.Projects without a usable IPA rating are not assigned a total analytical risk score.
A78: 4.Midpoint values are used where Low/Mid/High cost ranges are reported.
A79: 5.Missing dates reduce the number of projects included in duration analysis.
A80: 6.Comparisons between years may reflect projects entering or leaving the portfolio, as well as changes to existing projects.
A81: 7.Department names were standardised for modelling consistency.
A82: 8.The model should support prioritisation and investigation, not replace detailed project assurance.
A86: To refresh the workbook, replace or add annual source files using the established naming and column-standardisation rules, then select Data → Refresh All.
